CHANGELOG
LICENSE
MANIFEST.in
README.rst
requirements.txt
setup.py
kaoru/__init__.py
kaoru/__main__.py
kaoru/app.py
kaoru/cli.py
kaoru/command.py
kaoru/config.py
kaoru/db.py
kaoru/log.py
kaoru/procutils.py
kaoru/security.py
kaoru/utils.py
kaoru.egg-info/PKG-INFO
kaoru.egg-info/SOURCES.txt
kaoru.egg-info/dependency_links.txt
kaoru.egg-info/entry_points.txt
kaoru.egg-info/requires.txt
kaoru.egg-info/top_level.txt
kaoru/commands/__init__.py
kaoru/commands/about.py
kaoru/commands/cancel.py
kaoru/commands/dryrun.py
kaoru/commands/hello.py
kaoru/commands/help.py
kaoru/commands/hibernate.py
kaoru/commands/poweroff.py
kaoru/commands/reboot.py
kaoru/commands/screenlock.py
kaoru/commands/screenshot.py
kaoru/commands/start.py
kaoru/commands/suspend.py
kaoru/commands/unknown.py