Metadata-Version: 1.1
Name: kaoru
Version: 0.5.0
Summary: A Telegram Bot as your personal IoT assistant
Home-page: https://github.com/axltxl/kaoru
Author: Alejandro Ricoveri
Author-email: alejandroricoveri@gmail.com
License: MIT
Download-URL: https://github.com/axltxl/kaoru/tarball/0.5.0
Keywords: telegram,iot
Platform: UNKNOWN
Classifier: Development Status :: 4 - Beta
Classifier: Environment :: Console	
Classifier: Natural Language :: English
Classifier: License :: OSI Approved :: MIT License
Classifier: Operating System :: POSIX
Classifier: Operating System :: POSIX :: Linux
Classifier: Topic :: Utilities
Classifier: Programming Language :: Python
Classifier: Programming Language :: Python :: 3.5
Classifier: Programming Language :: Python :: 3.4
Classifier: Programming Language :: Python :: 3.3
